MANIFEST.in
README.md
setup.py
docs/.nojekyll
docs/Makefile
docs/authors.rst
docs/clean.bash
docs/compile.bash
docs/conf.py
docs/examples.rst
docs/fix_rst.py
docs/home.md
docs/index.html
docs/index.rst
docs/intro.rst
docs/license.rst
docs/task.rst
docs/thread.rst
docs/threadtask.rst
docs/_build/doctrees/authors.doctree
docs/_build/doctrees/environment.pickle
docs/_build/doctrees/examples.doctree
docs/_build/doctrees/index.doctree
docs/_build/doctrees/intro.doctree
docs/_build/doctrees/license.doctree
docs/_build/doctrees/task.doctree
docs/_build/doctrees/thread.doctree
docs/_build/doctrees/threadtask.doctree
docs/_build/html/.buildinfo
docs/_build/html/authors.html
docs/_build/html/examples.html
docs/_build/html/index.html
docs/_build/html/intro.html
docs/_build/html/license.html
docs/_build/html/objects.inv
docs/_build/html/search.html
docs/_build/html/searchindex.js
docs/_build/html/task.html
docs/_build/html/thread.html
docs/_build/html/threadtask.html
docs/_build/html/_downloads/a18b081f7d6dcca4c52c91e2f6deb6c3/hello_world.py
docs/_build/html/_downloads/a5acc46a2c9241a97e295f04f5174070/client.py
docs/_build/html/_downloads/c1dd4f4f2f4cf8025c3a2ba25bdb6544/parent_child.py
docs/_build/html/_downloads/e3e1e5e874df68c81d982fddd1e522aa/example_server2.py
docs/_build/html/_downloads/ef5c78e045abd894d5d4d0c53efb047e/example_server.py
docs/_build/html/_downloads/f924f640fe637e7f9e73bdbeaa5d3c81/client2.py
docs/_build/html/_sources/authors.rst.txt
docs/_build/html/_sources/examples.rst.txt
docs/_build/html/_sources/index.rst.txt
docs/_build/html/_sources/intro.rst.txt
docs/_build/html/_sources/license.rst.txt
docs/_build/html/_sources/task.rst.txt
docs/_build/html/_sources/thread.rst.txt
docs/_build/html/_sources/threadtask.rst.txt
docs/_build/html/_static/basic.css
docs/_build/html/_static/doctools.js
docs/_build/html/_static/documentation_options.js
docs/_build/html/_static/file.png
docs/_build/html/_static/jquery-3.5.1.js
docs/_build/html/_static/jquery.js
task_virtualthread.egg-info/PKG-INFO
task_virtualthread.egg-info/SOURCES.txt
task_virtualthread.egg-info/dependency_links.txt
task_virtualthread.egg-info/requires.txt
task_virtualthread.egg-info/top_level.txt