Metadata-Version: 2.1
Name: task-virtualthread
Version: 0.0.3
Summary: TaskThread: asyncio made easy
Home-page: https://elsampsa.github.io/task_thread/
Author: Sampsa Riikonen
Author-email: sampsa.riikonen@iki.fi
License: MIT
Keywords: python sphinx packaging
Platform: UNKNOWN
Classifier: Development Status :: 4 - Beta
Classifier: Intended Audience :: Developers
Classifier: License :: OSI Approved :: MIT License
Classifier: Programming Language :: Python :: 3
Classifier: Programming Language :: Python :: 3.8
Classifier: Programming Language :: Python :: 3.9
Classifier: Programming Language :: Python :: 3.10
